{
  "source_file": "friuli-venezia-giulia/CHURCH/.comuni/claut.md",
  "region": "friuli-venezia-giulia",
  "category": "CHURCH",
  "comune_name": "Claut",
  "province": "PN",
  "page_title": "Claut",
  "page_summary": "Guida alle principali chiese e luoghi di culto del comune di Claut: la chiesa arcipretale di San Giorgio Martire e la rete diffusa di cappelle votive e oratori nelle frazioni.",
  "source_url": "kb/friuli-venezia-giulia/CHURCH/.comuni/claut.md",
  "processed_at": "2026-04-09T12:33:18.956Z",
  "chunks": [
    {
      "chunk_id": "friuli-venezia-giulia/CHURCH/claut__0",
      "text": "### Chiesa Arcipretale di San Giorgio Martire\n\n**Comune:** Claut (capoluogo)\n**Indirizzo:** Piazza San Giorgio, 4 – 33080 Claut (PN)\n**Contatto:** tel. +39 0427 878078\n**Stile architettonico:** Neoclassico\n**Epoca di costruzione:** 1820–1828 (consacrazione: 1851)\n**Diocesi:** Concordia-Pordenone (Forania di Maniago)\n**Sito web di riferimento:** [pordenonewithlove.it](https://www.pordenonewithlove.it/it/cosa-fare/cultura/architetture/chiesa-parrocchiale-di-s-giorgio-martire) · [BeWeB CEI](https://www.beweb.chiesacattolica.it/edificidiculto/edificio/65508/)\n\nLa chiesa parrocchiale di San Giorgio Martire è l'edificio di culto principale di Claut e rappresenta la testimonianza architettonica più rilevante dell'intero comune. L'attuale costruzione è il frutto di una ricostruzione integrale avviata nei primi decenni dell'Ottocento: l'antico edificio sacro medievale fu demolito per far posto a un nuovo luogo di culto di impianto neoclassico, iniziato intorno al 1820 e portato a termine nel 1828. La chiesa fu consacrata nel 1851.\n\n**Origini e storia ecclesiastica**\n\nLe origini della parrocchia clautana affondano nel Medioevo. La chiesa era filiale della pieve di Cimolais, la cui matrice è attestata documentalmente già nel 1332, ma la cui dipendenza dall'Abbazia di Sesto al Reghena risale probabilmente all'VIII secolo. Come tutta la val Cellina, Claut gravitava ecclesiasticamente attorno al grande Patriarcato di Aquileia. Nel 1607 la chiesa fu emancipata dalla matrice pievanale di Cimolais, acquisendo autonomia parrocchiale. Nel 1818 passò alla Diocesi di Concordia, e nel 1955, dopo la rinuncia al giuspatronato da parte dei capifamiglia del paese, fu elevata al rango di **arcipretale**.\n\nL'edificio subì lavori di adeguamento liturgico nel 1970, in conformità alle direttive postconciliari, con l'introduzione dell'altare rivolto verso l'assemblea. L'ambone fu aggiunto vent'anni dopo, nel 1990. Tra il 2003 e il 2008 furono eseguiti restauri alle sagrestie, al campanile e alle facciate esterne.\n\n**Architettura**\n\nLa facciata, rivolta a nord, è di tipo **a capanna** e presenta un'impostazione solenne tipica del neoclassicismo provinciale dell'epoca. È scandita da quattro **lesene con capitelli d'ordine ionico** che sorreggono il **frontone triangolare**, entro il quale si apre un **oculo** circolare. Il portale d'ingresso è sormontato da un **timpano** che riprende le linee classiciste dell'insieme.\n\nL'interno è ad **unica navata** ampia e luminosa, con cappelle laterali aperte da **archi a tutto sesto**. Le pareti sono articolate da lesene ioniche che sorreggono la trabeazione modanata e aggettante, sopra la quale si imposta una **volta a botte**. Il presbiterio, rialzato di alcuni gradini rispetto all'aula, è chiuso dall'**abside**.\n\nAccanto alla parrocchiale si erge il **campanile**, costruito tra il 1852 e il 1853 su basamento in pietra. Con i suoi **37 metri di altezza** a base quadrata, la torre è un punto di riferimento visivo nell'intero fondovalle. La **cella campanaria** è aperta da bifore su ogni lato ed è coronata da una guglia poggiante su tamburo ottagonale. Le campane originali, ereditate dalla chiesa precedente, si rivelarono inadeguate e furono sostituite nel 1867 con nuovi esemplari fusi dalla **fonderia cenedese De Poli**.\n\n**Opere d'arte**\n\nL'interno custodisce un nucleo significativo di opere d'arte sacra che spazia dal XVII al XX secolo:\n\n- **Altari e statue di Giovanni Auregne** (bottega cadorina, XVII–XVIII sec.): la bottega veneta degli Auregne – artigiani del legno attivi tra il Cadore e le valli friulane – ha lasciato a Claut testimonianze di alto livello. Di questa mano sono l'**altare laterale ligneo**, finemente intagliato, dorato e dipinto, nonché un insieme di statue di devozione. La stessa bottega cadorina è responsabile degli altari analoghi presenti nella pieve matrice di Cimolais, segno di una committenza artistica condivisa nell'intera val Cellina.\n\n- **Altari del Sacro Cuore e di Sant'Antonio** (XVII sec.): due altari laterali di fattura seicentesca, testimonianza della stratificazione devozionale che caratterizza l'edificio prima della grande ricostruzione ottocentesca.\n\n- **Altare maggiore di Franz Martiner** (XIX–XX sec.): l'altare maggiore fu realizzato da Franz Martiner, scultore di tradizione centro-europea. Ai lati dell'altare sono collocate **statue lignee datate 1922**.\n\n- **Due pale d'altare di Ambrogio Chelm** (pittore austriaco, XVIII sec.): le due grandi tele che ornano l'aula raffigurano rispettivamente la **_Lavanda dei piedi_** e l'**_Ultima Cena_**. Ambrogio Chelm era un artista di formazione austriaca attivo nel territorio della diocesi durante l'età veneziana e asburgica.\n\n- **Ciclo di affreschi di Tiburzio Donadon** (primo Novecento): l'intervento più celebre e visivamente più impattante è il ciclo pittorico affrescato sui soffitti da **Tiburzio Donadon** (Motta di Livenza, 1881 – Pordenone, 1961), pittore e restauratore formatosi a Venezia che aprì una propria bottega a Pordenone nel 1915. Donadon fu uno degli artisti più attivi nella decorazione di edifici religiosi del Friuli tra le due guerre, ed è noto anche per i cicli pittorici del Santuario di Barbana a Grado e della Madonna delle Grazie a Pordenone. A Claut eseguì tre grandi scene: la **_Discesa della Manna nel deserto_**, l'**_Assunzione della Vergine in cielo_** e i **_Quattro Evangelisti_**. Lo stile di Donadon, ispirato al Liberty e alle correnti del Novecento, è caratterizzato da una frequente presenza di figure angeliche, trattate con eleganza narrativa e chiaroscurale.\n\n**Nota sulla committenza locale**\n\nLa ricchezza degli arredi interni della parrocchiale clautana è in parte da ricondurre alla tradizione dei **sedoneri**, le venditrici ambulanti di cucchiai e oggetti artigianali che percorrevano le pianure venete e friulane. Queste donne erano legate a un gergo segreto (il *dhèrbol*) e contribuivano, con i loro proventi, al sostentamento delle famiglie e alla commissione di arredi sacri. La comunità clautana, pur nella sua marginalità geografica, mantenne nei secoli una vivace capacità di investimento nel patrimonio religioso.",
      "metadata": {
        "section_title": "Chiesa Arcipretale di San Giorgio Martire",
        "links": [
          {
            "text": "pordenonewithlove.it",
            "url": "https://www.pordenonewithlove.it/it/cosa-fare/cultura/architetture/chiesa-parrocchiale-di-s-giorgio-martire"
          },
          {
            "text": "BeWeB CEI",
            "url": "https://www.beweb.chiesacattolica.it/edificidiculto/edificio/65508/"
          }
        ],
        "addresses": [
          "Piazza San Giorgio, 4 – 33080 Claut (PN)"
        ],
        "image_urls": [],
        "opening_hours": null,
        "prices": null
      }
    },
    {
      "chunk_id": "friuli-venezia-giulia/CHURCH/claut__1",
      "text": "### Cappelle Votive e Oratori delle Frazioni\n\n**Comune:** Claut e frazioni\n**Stile:** edilizio rurale montano\n**Epoca:** XVII–XIX sec. (con interventi successivi)\n\nCome è tipico dei comuni montani del Friuli occidentale, il territorio di Claut è punteggiato da una serie di **piccole cappelle votive, oratori e edicole sacre** distribuite nelle frazioni e lungo i sentieri della val Cellina e della val Settimana. Queste strutture minori — spesso intitolate alla Vergine o ai santi patroni locali — costituivano punti di riferimento spirituale per le comunità sparse nell'ampio territorio comunale, il più vasto dell'intera provincia di Pordenone.\n\nLe frazioni di Lesis, Matan, Pinedo, Cellino di Sopra e Cellino di Sotto, Creppi, Contrón e le borgate del capoluogo (Basoia, Massurìe, Mariáe) ospitano ciascuna strutture di culto semplici, generalmente a navata unica o anche prive di navata propria, con interni sobri che rispecchiano la cultura materiale alpina. Alcune di queste cappelle conservano piccole pale d'altare, statue devozionali in legno intagliato o affreschi votivi di artigiani locali anonimi o di botteghe itineranti.\n\nLa documentazione sistematica di questi edifici minori è frammentaria, ma il loro insieme costituisce una **rete capillare di devozione popolare** che si stratifica nei secoli e che integra, sul piano spirituale e comunitario, la funzione della grande parrocchiale del capoluogo. La visita al territorio di Claut consente di scoprire questa dimensione devozionale diffusa lungo i sentieri che attraversano il Parco Naturale delle Dolomiti Friulane.",
      "metadata": {
        "section_title": "Cappelle Votive e Oratori delle Frazioni",
        "links": [],
        "addresses": [],
        "image_urls": [],
        "opening_hours": null,
        "prices": null
      }
    }
  ]
}