{
  "source_file": "friuli-venezia-giulia/LANDMARK/.comuni/carlino.md",
  "region": "friuli-venezia-giulia",
  "category": "LANDMARK",
  "comune_name": "Carlino",
  "province": "UD",
  "page_title": "Carlino",
  "page_summary": "Guida ai principali landmark storici e religiosi del comune di Carlino: la Chiesa Parrocchiale di San Tommaso Apostolo e la Chiesa dei Santi Gervasio e Protasio nella frazione di San Gervasio.",
  "source_url": "kb/friuli-venezia-giulia/LANDMARK/.comuni/carlino.md",
  "processed_at": "2026-04-09T12:53:59.762Z",
  "chunks": [
    {
      "chunk_id": "friuli-venezia-giulia/LANDMARK/carlino__0",
      "text": "### Chiesa Parrocchiale di San Tommaso Apostolo (detto Becket)\n\n**Comune:** Carlino  \n**Epoca:** XVIII secolo  \n**Stile:** Barocco–neoclassico\n\nLa chiesa parrocchiale di Carlino è dedicata a san Tommaso Apostolo, identificato nella devozione locale con Tommaso Becket, il celebre arcivescovo di Canterbury martirizzato nel 1170 e canonizzato appena tre anni dopo dal papa Alessandro III. Il culto di Becket si diffuse ampiamente nel Medioevo lungo le rotte mercantili e pellegrinali che attraversavano il Friuli verso l'Europa centrale, e la sua presenza come patrono di Carlino attesta la permeabilità culturale di questa area di transito tra il mondo mediterraneo e quello alpino-danubiano.\n\nL'edificio attuale fu costruito nel XVIII secolo in sostituzione di un luogo di culto più antico, seguendo i canoni stilistici del tardo barocco friulano con influssi neoclassici tipici del periodo veneziano. La pianta è a navata unica con cappelle laterali; la facciata, sobria nei volumi, è coronata da un timpano triangolare e aperta da un portale modanato. Il campanile si erge robusto a fianco della navata, elemento caratteristico del paesaggio del paese.\n\nAll'interno, l'opera di maggior pregio è una **tela attribuita a Michelangelo Grigoletti** (Portogruaro, 1801–Venezia, 1870), pittore veneto di fama nazionale, autore di numerose pale d'altare destinate a chiese del Friuli e del Veneto. Grigoletti fu allievo di Lattanzio Querena e si formò all'Accademia di Belle Arti di Venezia, divenendo poi uno dei rappresentanti più apprezzati della pittura religiosa romantica dell'Italia nord-orientale. La presenza di una sua opera a Carlino è significativa e testimonia come anche le parrocchie minori della pianura friulana sapessero commissionare lavori ad artisti di rango.\n\nLa chiesa è il fulcro della vita religiosa e civile del paese; il patrono san Tommaso viene festeggiato il 21 dicembre, data che coincide con il solstizio d'inverno e con antichissime tradizioni popolari legate al ciclo agricolo.\n\n**Indirizzo:** Piazza della Chiesa, Carlino (UD)  \n**Sito web:** [www.comune.carlino.ud.it](http://www.comune.carlino.ud.it)",
      "metadata": {
        "section_title": "Chiesa Parrocchiale di San Tommaso Apostolo (detto Becket)",
        "links": [
          {
            "text": "www.comune.carlino.ud.it",
            "url": "http://www.comune.carlino.ud.it"
          }
        ],
        "addresses": [
          "Piazza della Chiesa, Carlino (UD)"
        ],
        "image_urls": [],
        "opening_hours": null,
        "prices": null
      }
    },
    {
      "chunk_id": "friuli-venezia-giulia/LANDMARK/carlino__1",
      "text": "### Chiesa dei Santi Gervasio e Protasio — Frazione di San Gervasio\n\n**Comune:** Carlino, frazione San Gervasio  \n**Epoca:** Origini medievali (IX sec. ipotetico); rifondazione documentata 1584; ampliamenti 1690, 1908  \n**Stile:** Rurale devozionale, con interventi di restauro novecentesco\n\nLa chiesa dei Santi Gervasio e Protasio, posta nella frazione omonima a pochi chilometri dal capoluogo comunale, è il più antico edificio di culto esistente nel territorio di Carlino. La sua storia affonda radici nell'Alto Medioevo: la tradizione locale e alcune tracce documentarie suggeriscono l'esistenza di un primitivo oratorio sul medesimo sito già nel IX secolo, probabilmente legato alla diffusione del Cristianesimo nella Bassa Friulana durante il periodo carolingio o postcarolingio.\n\nL'edificio che ancora oggi si può visitare fu eretto nel **1584**, come attesta un elemento lapideo — probabilmente un architrave — recante tale data incisa, oggi inserito nel muro della sacrestia. Il 1584 è un anno di particolare rilevanza nella storia religiosa friulana: coincide con il pieno dispiegamento della Controriforma post-tridentina, che in tutta la diocesi di Aquileia (e poi Udine) promosse la costruzione e il rinnovo di numerose cappelle e chiese campestri come strumento di radicamento pastorale nelle comunità rurali.\n\nNel **1690** l'edificio fu ampliato con la costruzione di un nuovo coro e la realizzazione dell'altare, interventi che rispecchiano il fervore edilizio barocco che caratterizzò il Friuli nel tardo Seicento, dopo le devastazioni dei terremoti e delle pestilenze del secolo precedente. L'assetto spaziale della chiesa fu ulteriormente modificato nel **1908**, quando una radicale ristrutturazione adeguò l'edificio ai gusti e alle esigenze liturgiche del primo Novecento.\n\nI santi titolari, Gervasio e Protasio, sono due martiri milanesi i cui resti furono ritrovati da sant'Ambrogio nel 386 e da lui traslati nella basilica Ambrosiana. Il loro culto si irradiò rapidamente nell'Italia settentrionale e nella pianura padano-veneta, diventando particolarmente radicato nelle campagne del Friuli. La scelta di questi santi come protettori della piccola frazione di San Gervasio è dunque coerente con una devozione profondamente ancorata alla tradizione liturgica ambrosiano-aquileiese che per secoli influenzò la spiritualità popolare di questa regione.\n\nLa chiesa, immersa nel paesaggio agricolo della Bassa Friulana, è un esempio eloquente di architettura rurale devozionale: sobria nelle forme esterne, raccolta nell'interno, rappresenta per la comunità un luogo di memoria collettiva che attraversa undici secoli di storia — dalle prime evangelizzazioni medievali fino al presente.\n\n**Indirizzo:** Via San Gervasio, San Gervasio — Carlino (UD)",
      "metadata": {
        "section_title": "Chiesa dei Santi Gervasio e Protasio — Frazione di San Gervasio",
        "links": [],
        "addresses": [
          "Via San Gervasio, San Gervasio — Carlino (UD)"
        ],
        "image_urls": [],
        "opening_hours": null,
        "prices": null
      }
    }
  ]
}